bin/hy-nrepl
hy_nrepl/__init__.hy
hy_nrepl/__init__.py
hy_nrepl/bencode.hy
hy_nrepl/server.hy
hy_nrepl/session.hy
hy_nrepl/middleware/__init__.hy
hy_nrepl/middleware/__init__.py
hy_nrepl/ops/__init__.hy
hy_nrepl/ops/__init__.py
hy_nrepl/ops/clone.hy
hy_nrepl/ops/close.hy
hy_nrepl/ops/completions.hy
hy_nrepl/ops/describe.hy
hy_nrepl/ops/eval.hy
hy_nrepl/ops/lookup.hy
hy_nrepl/ops/ls_sessions.hy
hy_nrepl/ops/stdin.hy
hy_nrepl/ops/utils.hy
hy_nrepl-1.0.4.data/scripts/hy-nrepl
hy_nrepl-1.0.4.dist-info/licenses/LICENSE
hy_nrepl-1.0.4.dist-info/METADATA
hy_nrepl-1.0.4.dist-info/WHEEL
hy_nrepl-1.0.4.dist-info/top_level.txt
hy_nrepl-1.0.4.dist-info/RECORD
