Metadata-Version: 2.4
Name: hy-nrepl
Version: 1.0.4
Summary: nREPL implementation for Hy (Hylang)
Author: Morten Linderud, Gregor Best, Satoshi Imai
License: MIT
Project-URL: Homepage, https://github.com/masatoi/hy-nrepl
Project-URL: Issues, https://github.com/masatoi/hy-nrepl/issues
Project-URL: CI, https://github.com/masatoi/hy-nrepl/actions
Keywords: hy,hylang,nrepl,repl
Classifier: Development Status :: 3 - Alpha
Classifier: Intended Audience :: Developers
Classifier: License :: OSI Approved :: MIT License
Classifier: Operating System :: OS Independent
Classifier: Programming Language :: Python
Classifier: Programming Language :: Python :: 3
Classifier: Programming Language :: Python :: 3 :: Only
Classifier: Programming Language :: Python :: 3.11
Classifier: Programming Language :: Lisp
Classifier: Topic :: Software Development :: Libraries
Requires-Python: >=3.11
License-File: LICENSE
Requires-Dist: hy>=0.29.0
Requires-Dist: hyrule>=0.6.0
Requires-Dist: toolz
Provides-Extra: test
Requires-Dist: pytest>=8.3; extra == "test"
Dynamic: license-file
